deepsearch/__init__.py
deepsearch/ingestion.py
deepsearch/intercepting_stream.py
deepsearch/server.py
deepsearch/tools.py
deepsearch/test_scripts/test_search.py
deepsearch/utils/async_utils.py
deepsearch/utils/document_utils.py
deepsearch/utils/file_converter.py
deepsearch/utils/openrouter_utils.py
deepsearch/utils/pinecone_utils.py
deepsearch/utils/prompts.py
deepsearch/utils/retrieval_utils.py
deepsearch/utils/search_utils.py
deepsearch/utils/text_chunking.py
deepsearch/utils/upload_to_cloudflare.py
deepsearch_latest-0.3.8.dist-info/METADATA
deepsearch_latest-0.3.8.dist-info/WHEEL
deepsearch_latest-0.3.8.dist-info/entry_points.txt
deepsearch_latest-0.3.8.dist-info/RECORD
