Metadata-Version: 2.4
Name: deepsearch-latest
Version: 0.3.8
Summary: Deep search tool for document analysis
Requires-Python: >=3.10
Requires-Dist: aioboto3
Requires-Dist: aiohttp
Requires-Dist: boto3
Requires-Dist: httpx
Requires-Dist: matplotlib
Requires-Dist: mcp
Requires-Dist: numpy
Requires-Dist: pandas
Requires-Dist: pdf2image
Requires-Dist: pillow
Requires-Dist: pinecone
Requires-Dist: python-docx
Requires-Dist: python-dotenv
Requires-Dist: tiktoken
